certbot_access_server/__init__.py
certbot_access_server/_internal/__init__.py
certbot_access_server/_internal/asxmlrpcapi.py
certbot_access_server/_internal/installer_access_server.py
tests/__init__.py
tests/installer_access_server_test.py
tests/pytest.ini
tests/testdata/ca_bundle.txt
tests/testdata/cert.txt
tests/testdata/priv_key.txt
certbot_access_server-1.0.4.dist-info/LICENSE.txt
certbot_access_server-1.0.4.dist-info/METADATA
certbot_access_server-1.0.4.dist-info/WHEEL
certbot_access_server-1.0.4.dist-info/entry_points.txt
certbot_access_server-1.0.4.dist-info/top_level.txt
certbot_access_server-1.0.4.dist-info/RECORD
